LICENSE
MANIFEST.in
README.md
setup.py
msproteomics/__init__.py
msproteomics/diann_parquet_to_tsv.py
msproteomics/read_diann.py
msproteomics/sitereport.py
msproteomics.egg-info/PKG-INFO
msproteomics.egg-info/SOURCES.txt
msproteomics.egg-info/dependency_links.txt
msproteomics.egg-info/entry_points.txt
msproteomics.egg-info/not-zip-safe
msproteomics.egg-info/requires.txt
msproteomics.egg-info/top_level.txt
msproteomics/__pycache__/__init__.cpython-313.pyc
src/iq_pybind11.cpp
src/main.c
src/Eigen/CMakeLists.txt
src/Eigen/Cholesky
src/Eigen/CholmodSupport
src/Eigen/Core
src/Eigen/Dense
src/Eigen/Eigen
src/Eigen/Eigenvalues
src/Eigen/Geometry
src/Eigen/Householder
src/Eigen/IterativeLinearSolvers
src/Eigen/Jacobi
src/Eigen/LU
src/Eigen/MetisSupport
src/Eigen/OrderingMethods
src/Eigen/PaStiXSupport
src/Eigen/PardisoSupport
src/Eigen/QR
src/Eigen/QtAlignedMalloc
src/Eigen/SPQRSupport
src/Eigen/SVD
src/Eigen/Sparse
src/Eigen/SparseCholesky
src/Eigen/SparseCore
src/Eigen/SparseLU
src/Eigen/SparseQR
src/Eigen/StdDeque
src/Eigen/StdList
src/Eigen/StdVector
src/Eigen/SuperLUSupport
src/Eigen/UmfPackSupport
src/Eigen/src/Cholesky/LDLT.h
src/Eigen/src/Cholesky/LLT.h
src/Eigen/src/Cholesky/LLT_LAPACKE.h
src/Eigen/src/CholmodSupport/CholmodSupport.h
src/Eigen/src/Core/Array.h
src/Eigen/src/Core/ArrayBase.h
src/Eigen/src/Core/ArrayWrapper.h
src/Eigen/src/Core/Assign.h
src/Eigen/src/Core/AssignEvaluator.h
src/Eigen/src/Core/Assign_MKL.h
src/Eigen/src/Core/BandMatrix.h
src/Eigen/src/Core/Block.h
src/Eigen/src/Core/BooleanRedux.h
src/Eigen/src/Core/CommaInitializer.h
src/Eigen/src/Core/ConditionEstimator.h
src/Eigen/src/Core/CoreEvaluators.h
src/Eigen/src/Core/CoreIterators.h
src/Eigen/src/Core/CwiseBinaryOp.h
src/Eigen/src/Core/CwiseNullaryOp.h
src/Eigen/src/Core/CwiseTernaryOp.h
src/Eigen/src/Core/CwiseUnaryOp.h
src/Eigen/src/Core/CwiseUnaryView.h
src/Eigen/src/Core/DenseBase.h
src/Eigen/src/Core/DenseCoeffsBase.h
src/Eigen/src/Core/DenseStorage.h
src/Eigen/src/Core/Diagonal.h
src/Eigen/src/Core/DiagonalMatrix.h
src/Eigen/src/Core/DiagonalProduct.h
src/Eigen/src/Core/Dot.h
src/Eigen/src/Core/EigenBase.h
src/Eigen/src/Core/ForceAlignedAccess.h
src/Eigen/src/Core/Fuzzy.h
src/Eigen/src/Core/GeneralProduct.h
