Metadata-Version: 2.2
Name: msproteomics
Version: 1.1.0
Summary: A Python package for mass spectrometry-based proteomics data processing
Home-page: https://github.com/tvpham/msproteomics
Author: Thang Pham
Author-email: t.pham@amsterdamumc.nl
License: Apache License 2.0
Classifier: Development Status :: 5 - Production/Stable
Classifier: Intended Audience :: Science/Research
Classifier: License :: OSI Approved :: Apache Software License
License-File: LICENSE
Requires-Dist: numpy
Requires-Dist: pandas
Requires-Dist: matplotlib
Dynamic: author
Dynamic: author-email
Dynamic: classifier
Dynamic: description
Dynamic: description-content-type
Dynamic: home-page
Dynamic: license
Dynamic: requires-dist
Dynamic: summary
